llama_index/readers/toggl/__init__.py
llama_index/readers/toggl/base.py
llama_index/readers/toggl/dto.py
llama_index_readers_toggl-0.4.1.dist-info/METADATA
llama_index_readers_toggl-0.4.1.dist-info/WHEEL
llama_index_readers_toggl-0.4.1.dist-info/licenses/LICENSE
llama_index_readers_toggl-0.4.1.dist-info/RECORD
